explainable_ai_image_measures/__init__.py
explainable_ai_image_measures/irof.py
explainable_ai_image_measures/pixel_manipulation.py
explainable_ai_image_measures/pixel_relevancy.py
explainable_ai_image_measures/scoring_metric.py
explainable_ai_image_measures-1.0.1.dist-info/LICENSE
explainable_ai_image_measures-1.0.1.dist-info/METADATA
explainable_ai_image_measures-1.0.1.dist-info/WHEEL
explainable_ai_image_measures-1.0.1.dist-info/top_level.txt
explainable_ai_image_measures-1.0.1.dist-info/RECORD
