Metadata-Version: 2.1
Name: explainable-ai-image-measures
Version: 1.0.1
Summary: Compute IAUC, DAUC, IROF scores to measure quality of image attributions
Home-page: https://github.com/Meier-Johannes/ExplainableAIImageMeasures
Author: Johannes Meier
Author-email: johannes-michael.meier@student.uni-tuebingen.de
License: MIT
Platform: UNKNOWN
Classifier: License :: OSI Approved :: MIT License
Classifier: Programming Language :: Python :: 3
Classifier: Programming Language :: Python :: 3.8
Requires-Dist: numpy
Requires-Dist: torch
Requires-Dist: scikit-image
Requires-Dist: scikit-learn
